[{"word":"the","count":3670},{"word":"is","count":2819},{"word":"of","count":2630},{"word":"in","count":2070},{"word":"amp","count":1908},{"word":"for","count":1764},{"word":"will","count":1419},{"word":"be","count":1354},{"word":"on","count":1238},{"word":"that","count":1192},{"word":"it","count":1183},{"word":"but","count":1098},{"word":"tesla","count":1057},{"word":"this","count":1020},{"word":"we","count":910},{"word":"with","count":905},{"word":"are","count":832},{"word":"not","count":773},{"word":"you","count":767},{"word":"at","count":745}]